__init__.py
_fit/__init__.py
_fit/_fit_function_1d.py
_fit/_fit_functions_2d.py
_fit/fit.py
histograms/__init__.py
histograms/bins.py
histograms/histogram_1d.py
histograms/histogram_2d.py
histograms/histogram_base.py
tools/__init__.py
tools/data_checker.py
root_histogram-0.0.1.dist-info/LICENCE
root_histogram-0.0.1.dist-info/METADATA
root_histogram-0.0.1.dist-info/WHEEL
root_histogram-0.0.1.dist-info/top_level.txt
root_histogram-0.0.1.dist-info/RECORD
